luna_paysure
