Metadata-Version: 2.1
Name: luna-paysure
Version: 0.7.4
Summary: A very interesting package
Home-page: UNKNOWN
Author: Peter Rabbit
Author-email: prabbit@gmail.com
License: UNKNOWN
Platform: UNKNOWN
Classifier: Programming Language :: Python :: 3
Classifier: License :: OSI Approved :: MIT License
Classifier: Operating System :: OS Independent
Requires-Python: >=3.6
